<?xml version="1.0" encoding="utf-8" ?>
<dwsync>
<file name="index.htm" server="is-israel.com//is-israel.com/" local="129685309707932455" remote="129952414800000000" />
<file name="gmalim.gdb" server="is-israel.com//is-israel.com/" local="129501129103185399" remote="129952414800000000" />
<file name="gmalim.kmz" server="is-israel.com//is-israel.com/" local="129501130028878346" remote="129952414800000000" />
<file name="gmalim.plt" server="is-israel.com//is-israel.com/" local="129474122698945182" remote="129952414800000000" />
<file name="gmalim.rte" server="is-israel.com//is-israel.com/" local="129501127720366306" remote="129952414800000000" />
<file name="gmalim.twl" server="is-israel.com//is-israel.com/" local="128508469905937500" remote="129952414800000000" />
<file name="gmalim.wpt" server="is-israel.com//is-israel.com/" local="129501127552386698" remote="129952414800000000" />
<file name="gmalimMS.trk" server="is-israel.com//is-israel.com/" local="128508602762500000" remote="129952414800000000" />
<file name="gmalimMS.wpt" server="is-israel.com//is-israel.com/" local="128508602975312500" remote="129952414800000000" />
<file name="mapa.gif" server="is-israel.com//is-israel.com/" local="128508574357031250" remote="129952414800000000" />
<file name="mapai.gif" server="is-israel.com//is-israel.com/" local="128508574645312500" remote="129952414800000000" />
<file name="mapat.gif" server="is-israel.com//is-israel.com/" local="128508566123906250" remote="129952415400000000" />
<file name="mapat1.gif" server="is-israel.com//is-israel.com/" local="128508569853437500" remote="129952415400000000" />
<file name="mapat1i.gif" server="is-israel.com//is-israel.com/" local="128508570043125000" remote="129952415400000000" />
<file name="mapati.gif" server="is-israel.com//is-israel.com/" local="128508566359218750" remote="129952415400000000" />
<file name="profil.gif" server="is-israel.com//is-israel.com/" local="128508574950937500" remote="129952415400000000" />
<file name="profili.gif" server="is-israel.com//is-israel.com/" local="128508575377656250" remote="129952415400000000" />
<file name="gmalim.gpx" server="is-israel.com//is-israel.com/" local="129501128070456330" remote="129952414800000000" />
<file name="gmalim.gdb" server="velik.org" local="129501129103185399" remote="131251645200000000" />
<file name="gmalim.gpx" server="velik.org" local="129501128070456330" remote="131251645200000000" />
<file name="gmalim.kmz" server="velik.org" local="129501130028878346" remote="131251645200000000" />
<file name="gmalim.plt" server="velik.org" local="129474122698945182" remote="131251645200000000" />
<file name="gmalim.rte" server="velik.org" local="129501127720366306" remote="131251645200000000" />
<file name="gmalim.twl" server="velik.org" local="128508469905937500" remote="131251645200000000" />
<file name="gmalim.wpt" server="velik.org" local="129501127552386698" remote="131251645200000000" />
<file name="gmalimMS.trk" server="velik.org" local="128508602762500000" remote="131251645200000000" />
<file name="gmalimMS.wpt" server="velik.org" local="128508602975312500" remote="131251645200000000" />
<file name="index.htm" server="velik.org" local="131251642674719890" remote="131251645200000000" />
<file name="mapa.gif" server="velik.org" local="128508574357031250" remote="131251645200000000" />
<file name="mapai.gif" server="velik.org" local="128508574645312500" remote="131251645200000000" />
<file name="mapat.gif" server="velik.org" local="128508566123906250" remote="131251645200000000" />
<file name="mapat1.gif" server="velik.org" local="128508569853437500" remote="131251645200000000" />
<file name="mapat1i.gif" server="velik.org" local="128508570043125000" remote="131251645200000000" />
<file name="mapati.gif" server="velik.org" local="128508566359218750" remote="131251645800000000" />
<file name="profil.gif" server="velik.org" local="128508574950937500" remote="131251645800000000" />
<file name="profili.gif" server="velik.org" local="128508575377656250" remote="131251645800000000" />
</dwsync>