<?xml version="1.0" encoding="utf-8" ?>
<dwsync>
<file name="ayalon.gdb" server="is-israel.com//is-israel.com/" local="129481840667233017" remote="129952389600000000" />
<file name="ayalon.jpg" server="is-israel.com//is-israel.com/" local="127875676200000000" remote="129952389600000000" />
<file name="ayalon.kmz" server="is-israel.com//is-israel.com/" local="129481843489524442" remote="129952389600000000" />
<file name="ayalon.plt" server="is-israel.com//is-israel.com/" local="129474034985088237" remote="129952389600000000" />
<file name="ayalon.rte" server="is-israel.com//is-israel.com/" local="129481537440903874" remote="129952389600000000" />
<file name="ayalon.twl" server="is-israel.com//is-israel.com/" local="129481844986550067" remote="129952389600000000" />
<file name="ayalon.wpt" server="is-israel.com//is-israel.com/" local="129481537220261254" remote="129952389600000000" />
<file name="ayalon037.jpg" server="is-israel.com//is-israel.com/" local="127875634800000000" remote="129952389600000000" />
<file name="ayalon1.gif" server="is-israel.com//is-israel.com/" local="127875635400000000" remote="129952389600000000" />
<file name="ayaloni.jpg" server="is-israel.com//is-israel.com/" local="127875680400000000" remote="129952389600000000" />
<file name="index.htm" server="is-israel.com//is-israel.com/" local="129684339579574287" remote="129952389600000000" />
<file name="mapa.gif" server="is-israel.com//is-israel.com/" local="129481852829438655" remote="129952389600000000" />
<file name="mapai.gif" server="is-israel.com//is-israel.com/" local="129481853129025790" remote="129952389600000000" />
<file name="mapat.gif" server="is-israel.com//is-israel.com/" local="129481846838465991" remote="129952390200000000" />
<file name="mapati.gif" server="is-israel.com//is-israel.com/" local="129481847107511379" remote="129952390200000000" />
<file name="profil.gif" server="is-israel.com//is-israel.com/" local="128057131778750000" remote="129952390200000000" />
<file name="profili.gif" server="is-israel.com//is-israel.com/" local="128057131970468752" remote="129952390200000000" />
<file name="ayalon.gpx" server="is-israel.com//is-israel.com/" local="129481839266092876" remote="129952389600000000" />
<file name="mapat1.gif" server="is-israel.com//is-israel.com/" local="129481849155818536" remote="129952390200000000" />
<file name="mapat1i.gif" server="is-israel.com//is-israel.com/" local="129481848386904557" remote="129952390200000000" />
<file name="ayalon.gdb" server="velik.org" local="129481840667233017" remote="131251641000000000" />
<file name="ayalon.gpx" server="velik.org" local="129481839266092876" remote="131251641000000000" />
<file name="ayalon.jpg" server="velik.org" local="127875676200000000" remote="131251641000000000" />
<file name="ayalon.kmz" server="velik.org" local="129481843489524442" remote="131251641000000000" />
<file name="ayalon.plt" server="velik.org" local="129474034985088237" remote="131251641000000000" />
<file name="ayalon.rte" server="velik.org" local="129481537440903874" remote="131251641000000000" />
<file name="ayalon.twl" server="velik.org" local="129481844986550067" remote="131251641000000000" />
<file name="ayalon.wpt" server="velik.org" local="129481537220261254" remote="131251641000000000" />
<file name="ayalon037.jpg" server="velik.org" local="127875634800000000" remote="131251641000000000" />
<file name="ayalon1.gif" server="velik.org" local="127875635400000000" remote="131251641000000000" />
<file name="ayaloni.jpg" server="velik.org" local="127875680400000000" remote="131251641000000000" />
<file name="index.htm" server="velik.org" local="131251642638996940" remote="131251641000000000" />
<file name="mapa.gif" server="velik.org" local="129481852829438655" remote="131251641000000000" />
<file name="mapai.gif" server="velik.org" local="129481853129025790" remote="131251641000000000" />
<file name="mapat.gif" server="velik.org" local="129481846838465991" remote="131251641000000000" />
<file name="mapat1.gif" server="velik.org" local="129481849155818536" remote="131251641000000000" />
<file name="mapat1i.gif" server="velik.org" local="129481848386904557" remote="131251641000000000" />
<file name="mapati.gif" server="velik.org" local="129481847107511379" remote="131251641000000000" />
<file name="profil.gif" server="velik.org" local="128057131778750000" remote="131251641000000000" />
<file name="profili.gif" server="velik.org" local="128057131970468752" remote="131251641000000000" />
</dwsync>